sloom/Crawler.py
sloom/Date.py
sloom/Fetcher.py
sloom/RequestError.py
sloom/Response.py
sloom/ResponseType.py
sloom/Responses.py
sloom/Scraper.py
sloom/Topic.py
sloom/__init__.py
sloom/__main__.py
sloom/href.py
sloom/news_api.py
sloom/webscrapper.py
sloom/Core/List.py
sloom/Core/Terminal.py
sloom/Core/__init__.py
src/Fetcher.py
src/RequestError.py
src/Response.py
src/ResponseType.py
src/Responses.py
src/__init__.py
src/news_api.py
src/webscrapper.py
src/Core/List.py
src/Core/Terminal.py
src/Core/__init__.py
sloom-0.2.2.dist-info/METADATA
sloom-0.2.2.dist-info/WHEEL
sloom-0.2.2.dist-info/top_level.txt
sloom-0.2.2.dist-info/RECORD
