Metadata-Version: 2.1
Name: sloom
Version: 0.2.2
Summary: Webscraper
Home-page: https://github.com/ReedHunsaker/Webscraper
Author: Reed Hunsaker
Author-email: reed.hunsaker@gmail.com
License: Apache License 2.0
Requires-Dist: requests
Requires-Dist: bs4
Requires-Dist: pytest
